{
  "profile_url": "https://ludzie.nauka.gov.pl/ln/profiles/marcin.jewartowski.4197L0aQmXc",
  "slug": "marcin.jewartowski",
  "profile_id": "4197L0aQmXc",
  "full_name": "dr inż. Marcin Jewartowski",
  "orcid": null,
  "orcid_url": null,
  "breadcrumb_name": "Marcin Jewartowski",
  "current_employment_summary": [
    "Politechnika Gdańska"
  ],
  "discipline_summary": [],
  "specializations": [
    "technologia spalania"
  ],
  "tab_menu": [
    {
      "label": "Profil",
      "href": "https://ludzie.nauka.gov.pl/ln/profiles/marcin.jewartowski.4197L0aQmXc",
      "aria_disabled": null
    },
    {
      "label": "Publikacje",
      "href": "https://ludzie.nauka.gov.pl/ln/profiles/marcin.jewartowski.4197L0aQmXc/publications",
      "aria_disabled": null
    },
    {
      "label": "Dorobek artystyczny",
      "href": "https://ludzie.nauka.gov.pl/ln/profiles/marcin.jewartowski.4197L0aQmXc/achievement",
      "aria_disabled": "true"
    },
    {
      "label": "Patenty i prawa ochronne",
      "href": "https://ludzie.nauka.gov.pl/ln/profiles/marcin.jewartowski.4197L0aQmXc/patents",
      "aria_disabled": null
    },
    {
      "label": "Projekty",
      "href": "https://ludzie.nauka.gov.pl/ln/profiles/marcin.jewartowski.4197L0aQmXc/projects",
      "aria_disabled": null
    },
    {
      "label": "Postępowania awansowe",
      "href": "https://ludzie.nauka.gov.pl/ln/profiles/marcin.jewartowski.4197L0aQmXc/research-work",
      "aria_disabled": null
    }
  ],
  "employment_history": [
    {
      "row_order": 0,
      "period": "16 lat 2 miesiące",
      "duration": null,
      "institution": "Politechnika Gdańska",
      "institution_url": "https://radon.nauka.gov.pl/dane/profil/76e7e103-e39c-48d6-8aa2-8fde70c50563",
      "source_json": [
        "Źródło danych: POL-on"
      ]
    }
  ],
  "degrees_and_titles": [
    {
      "row_order": 0,
      "year": "2009",
      "degree_or_title": "Doktor",
      "details_json": [
        "dziedzina nauk technicznych / budowa i eksploatacja maszyn",
        "Nadanie stopnia"
      ],
      "linked_entities_json": [
        {
          "label": "Politechnika Gdańska",
          "href": "https://radon.nauka.gov.pl/dane/profil/76e7e103-e39c-48d6-8aa2-8fde70c50563"
        }
      ],
      "source_json": [
        "Źródło danych: POL-on"
      ]
    },
    {
      "row_order": 1,
      "year": "2000",
      "degree_or_title": "Magister inżynier",
      "details_json": [
        "mechanika i budowa maszyn",
        "Nadanie tytułu",
        "Politechnika Gdańska",
        "Rejestracja tytułu"
      ],
      "linked_entities_json": [
        {
          "label": "Politechnika Gdańska >",
          "href": "https://radon.nauka.gov.pl/dane/profil/76e7e103-e39c-48d6-8aa2-8fde70c50563"
        }
      ],
      "source_json": [
        "Źródło danych: POL-on"
      ]
    }
  ],
  "memberships": [],
  "publications_preview": [
    {
      "row_order": 0,
      "title": "Modeling of low calorific gas burning in a deficient oxygen environment and high-temperature oxidizer",
      "title_url": "https://ludzie.nauka.gov.pl/ln/profiles/marcin.jewartowski.4197L0aQmXc/publications/2a440cc7-1df5-4729-b6ca-056371e02921",
      "authors": "J. Stąsiek, M. Jewartowski , J. Barański, ... (+1)",
      "publication_type": "Artykuł , International Journal of Physics Research and Applications",
      "year": "2023",
      "doi": "10.29328/journal.ijpra.1001050",
      "doi_url": "https://www.doi.org/10.29328/journal.ijpra.1001050",
      "source": "Źródło danych: Polska Bibliografia Naukowa"
    },
    {
      "row_order": 1,
      "title": "Optimisation of cooperation of hybrid renewable energy sources with hydrogen energy storage toward the lowest net present cost",
      "title_url": "https://ludzie.nauka.gov.pl/ln/profiles/marcin.jewartowski.4197L0aQmXc/publications/9b44242c-d4cb-4af9-bee4-d02d72a0b24a",
      "authors": "J. Łukasik, M. Jewartowski , J. Wajs",
      "publication_type": "Artykuł , Instal",
      "year": "2023",
      "doi": "10.36119/15.2023.12.2",
      "doi_url": "https://www.doi.org/10.36119/15.2023.12.2",
      "source": "Źródło danych: Polska Bibliografia Naukowa"
    },
    {
      "row_order": 2,
      "title": "Techno-economic assessment of cooperation of hybrid renewable energy sources with hydrogen storage",
      "title_url": "https://ludzie.nauka.gov.pl/ln/profiles/marcin.jewartowski.4197L0aQmXc/publications/1c0dea68-d66b-4a5a-b6c2-9a107a045569",
      "authors": "J. Łukasik, M. Jewartowski , J. Wajs",
      "publication_type": "Artykuł , Instal",
      "year": "2023",
      "doi": "10.36119/15.2023.11.3",
      "doi_url": "https://www.doi.org/10.36119/15.2023.11.3",
      "source": "Źródło danych: Polska Bibliografia Naukowa"
    }
  ],
  "research_work": {
    "author": [
      {
        "row_order": 0,
        "title": "Modelowanie spalania w pojedynczym płomieniu przy wysokotemperaturowym podgrzewie utleniacza",
        "title_url": "https://ludzie.nauka.gov.pl/ln/profiles/marcin.jewartowski.4197L0aQmXc/research-work/66cb56be-e186-49ef-b45d-d5eb2f00e13f",
        "description": "Praca doktorska Źródło danych: Nauka Polska",
        "source": "Źródło danych: Nauka Polska"
      }
    ],
    "promoter": [],
    "reviewer": []
  },
  "external_profiles": [
    {
      "label": "Nauka Polska",
      "url": "https://archiwum.nauka-polska.pl/#/profile/scientist?id=217505"
    }
  ],
  "tag_cloud": [
    "chip removing system",
    "sliding table saw",
    "heating systems, heat pump, solar energy, smart control, iot",
    "htag",
    "gasification",
    "biomass",
    "high temperature air/steam gasification",
    "wastes",
    "experimental study",
    "heat and electricity production"
  ],
  "coworkers": []
}