{
  "profile_url": "https://ludzie.nauka.gov.pl/ln/profiles/micha%C5%82.g%C5%82owacki.7DkiwUtYjb6",
  "slug": "michał.głowacki",
  "profile_id": "7DkiwUtYjb6",
  "full_name": "dr inż. Michał Jan Głowacki",
  "orcid": "0000-0003-2494-3225",
  "orcid_url": "https://orcid.org/0000-0003-2494-3225",
  "breadcrumb_name": "Michał Głowacki",
  "current_employment_summary": [
    "Politechnika Warszawska"
  ],
  "discipline_summary": [
    "dziedzina nauk inżynieryjno-technicznych"
  ],
  "specializations": [],
  "tab_menu": [
    {
      "label": "Profil",
      "href": "https://ludzie.nauka.gov.pl/ln/profiles/micha%C5%82.g%C5%82owacki.7DkiwUtYjb6",
      "aria_disabled": null
    },
    {
      "label": "Publikacje",
      "href": "https://ludzie.nauka.gov.pl/ln/profiles/micha%C5%82.g%C5%82owacki.7DkiwUtYjb6/publications",
      "aria_disabled": null
    },
    {
      "label": "Dorobek artystyczny",
      "href": "https://ludzie.nauka.gov.pl/ln/profiles/micha%C5%82.g%C5%82owacki.7DkiwUtYjb6/achievement",
      "aria_disabled": "true"
    },
    {
      "label": "Patenty i prawa ochronne",
      "href": "https://ludzie.nauka.gov.pl/ln/profiles/micha%C5%82.g%C5%82owacki.7DkiwUtYjb6/patents",
      "aria_disabled": "true"
    },
    {
      "label": "Projekty",
      "href": "https://ludzie.nauka.gov.pl/ln/profiles/micha%C5%82.g%C5%82owacki.7DkiwUtYjb6/projects",
      "aria_disabled": null
    },
    {
      "label": "Postępowania awansowe",
      "href": "https://ludzie.nauka.gov.pl/ln/profiles/micha%C5%82.g%C5%82owacki.7DkiwUtYjb6/research-work",
      "aria_disabled": null
    }
  ],
  "employment_history": [
    {
      "row_order": 0,
      "period": "16 lat 6 miesięcy",
      "duration": null,
      "institution": "Politechnika Warszawska",
      "institution_url": "https://radon.nauka.gov.pl/dane/profil/521ce6da-8ebb-47a5-90fe-3832685b75f9",
      "source_json": [
        "Źródło danych: POL-on"
      ]
    }
  ],
  "degrees_and_titles": [
    {
      "row_order": 0,
      "year": "2017",
      "degree_or_title": "Doktor",
      "details_json": [
        "dziedzina nauk technicznych / budownictwo",
        "Nadanie stopnia",
        "Rejestracja stopnia"
      ],
      "linked_entities_json": [
        {
          "label": "Politechnika Warszawska; Wydział Inżynierii Lądowej",
          "href": "https://radon.nauka.gov.pl/dane/profil/f99459a0-12ff-4940-87a5-175328e8e031"
        },
        {
          "label": "Politechnika Warszawska >",
          "href": "https://radon.nauka.gov.pl/dane/profil/521ce6da-8ebb-47a5-90fe-3832685b75f9"
        }
      ],
      "source_json": [
        "Źródło danych: POL-on"
      ]
    },
    {
      "row_order": 1,
      "year": "2009",
      "degree_or_title": "Magister inżynier",
      "details_json": [
        "budownictwo",
        "Nadanie tytułu",
        "Politechnika Warszawska",
        "Rejestracja tytułu"
      ],
      "linked_entities_json": [
        {
          "label": "Politechnika Warszawska >",
          "href": "https://radon.nauka.gov.pl/dane/profil/521ce6da-8ebb-47a5-90fe-3832685b75f9"
        }
      ],
      "source_json": [
        "Źródło danych: POL-on"
      ]
    }
  ],
  "memberships": [],
  "publications_preview": [
    {
      "row_order": 0,
      "title": "Dangerous damage of RC structural members caused by thermal spalling of concrete during fire in an enclosed car park of residential building",
      "title_url": "https://ludzie.nauka.gov.pl/ln/profiles/micha%C5%82.g%C5%82owacki.7DkiwUtYjb6/publications/923d6143-f3ea-4763-800d-d5c9f2c30e72",
      "authors": "R. Kowalski, M. Głowacki , J. Wróblewska, ... (+2)",
      "publication_type": "Artykuł , Fire Safety Journal",
      "year": "2025",
      "doi": "10.1016/j.firesaf.2025.104352",
      "doi_url": "https://www.doi.org/10.1016/j.firesaf.2025.104352",
      "source": "Źródło danych: Polska Bibliografia Naukowa"
    },
    {
      "row_order": 1,
      "title": "Disproportionately wide range of fire in a RC building during construction stage",
      "title_url": "https://ludzie.nauka.gov.pl/ln/profiles/micha%C5%82.g%C5%82owacki.7DkiwUtYjb6/publications/4b55a5a4-1408-4c02-bfff-a625d86e0fbd",
      "authors": "P. Knyziak, R. Kowalski, M. Głowacki , ... (+1)",
      "publication_type": "Artykuł , Engineering Failure Analysis",
      "year": "2022",
      "doi": "10.1016/j.engfailanal.2022.106260",
      "doi_url": "https://www.doi.org/10.1016/j.engfailanal.2022.106260",
      "source": "Źródło danych: Polska Bibliografia Naukowa"
    },
    {
      "row_order": 2,
      "title": "Simple consideration of second-order effects in the calculation of RC column fire resistance",
      "title_url": "https://ludzie.nauka.gov.pl/ln/profiles/micha%C5%82.g%C5%82owacki.7DkiwUtYjb6/publications/7cf748ed-7972-4650-8a55-8ca658803bf6",
      "authors": "M. Głowacki , R. Kowalski",
      "publication_type": "Artykuł , Fire Safety Journal",
      "year": "2022",
      "doi": "10.1016/j.firesaf.2022.103650",
      "doi_url": "https://www.doi.org/10.1016/j.firesaf.2022.103650",
      "source": "Źródło danych: Polska Bibliografia Naukowa"
    }
  ],
  "research_work": {
    "author": [
      {
        "row_order": 0,
        "title": "Sztywność zginanych elementów żelbetowych poddanych działaniu temperatury pożarowej",
        "title_url": "https://ludzie.nauka.gov.pl/ln/profiles/micha%C5%82.g%C5%82owacki.7DkiwUtYjb6/research-work/bcc38ded-2d82-45ae-ba52-063daa50437a",
        "description": "Praca doktorska Źródło danych: Nauka Polska",
        "source": "Źródło danych: Nauka Polska"
      }
    ],
    "promoter": [],
    "reviewer": []
  },
  "external_profiles": [
    {
      "label": "Nauka Polska",
      "url": "https://archiwum.nauka-polska.pl/#/profile/scientist?id=284139"
    }
  ],
  "tag_cloud": [
    "econstruction stage",
    "shear resistance",
    "deflection",
    "rc beams",
    "fire",
    "high temperature",
    "stiffness",
    "concrete",
    "beton zbrojony",
    "wysokie temperatury"
  ],
  "coworkers": []
}