{
  "profile_url": "https://ludzie.nauka.gov.pl/ln/profiles/marek.goli%C5%84ski.7SVtrNQCx6J",
  "slug": "marek.goliński",
  "profile_id": "7SVtrNQCx6J",
  "full_name": "dr inż. Marek Goliński",
  "orcid": "0000-0002-0170-2835",
  "orcid_url": "https://orcid.org/0000-0002-0170-2835",
  "breadcrumb_name": "Marek Goliński",
  "current_employment_summary": [
    "Politechnika Poznańska"
  ],
  "discipline_summary": [
    "dziedzina nauk społecznych"
  ],
  "specializations": [
    "marketing",
    "analiza rynku",
    "badania marketingowe",
    "zarządzanie jakością"
  ],
  "tab_menu": [
    {
      "label": "Profil",
      "href": "https://ludzie.nauka.gov.pl/ln/profiles/marek.goli%C5%84ski.7SVtrNQCx6J",
      "aria_disabled": null
    },
    {
      "label": "Publikacje",
      "href": "https://ludzie.nauka.gov.pl/ln/profiles/marek.goli%C5%84ski.7SVtrNQCx6J/publications",
      "aria_disabled": null
    },
    {
      "label": "Dorobek artystyczny",
      "href": "https://ludzie.nauka.gov.pl/ln/profiles/marek.goli%C5%84ski.7SVtrNQCx6J/achievement",
      "aria_disabled": "true"
    },
    {
      "label": "Patenty i prawa ochronne",
      "href": "https://ludzie.nauka.gov.pl/ln/profiles/marek.goli%C5%84ski.7SVtrNQCx6J/patents",
      "aria_disabled": "true"
    },
    {
      "label": "Projekty",
      "href": "https://ludzie.nauka.gov.pl/ln/profiles/marek.goli%C5%84ski.7SVtrNQCx6J/projects",
      "aria_disabled": "true"
    },
    {
      "label": "Postępowania awansowe",
      "href": "https://ludzie.nauka.gov.pl/ln/profiles/marek.goli%C5%84ski.7SVtrNQCx6J/research-work",
      "aria_disabled": null
    }
  ],
  "employment_history": [
    {
      "row_order": 0,
      "period": "29 lat 2 miesiące",
      "duration": null,
      "institution": "Politechnika Poznańska",
      "institution_url": "https://radon.nauka.gov.pl/dane/profil/2caf49c8-c982-4873-9175-a3fb2ca1ce99",
      "source_json": [
        "Źródło danych: POL-on"
      ]
    }
  ],
  "degrees_and_titles": [
    {
      "row_order": 0,
      "year": "2006",
      "degree_or_title": "Doktor",
      "details_json": [
        "nauki techniczne / budowa i eksploatacja maszyn",
        "Nadanie stopnia"
      ],
      "linked_entities_json": [
        {
          "label": "Politechnika Poznańska",
          "href": "https://radon.nauka.gov.pl/dane/profil/2caf49c8-c982-4873-9175-a3fb2ca1ce99"
        }
      ],
      "source_json": [
        "Źródło danych: POL-on"
      ]
    },
    {
      "row_order": 1,
      "year": "1995",
      "degree_or_title": "Magister inżynier",
      "details_json": [
        "zarządzanie i marketing",
        "Rejestracja tytułu"
      ],
      "linked_entities_json": [
        {
          "label": "Politechnika Poznańska >",
          "href": "https://radon.nauka.gov.pl/dane/profil/2caf49c8-c982-4873-9175-a3fb2ca1ce99"
        }
      ],
      "source_json": [
        "Źródło danych: POL-on"
      ]
    }
  ],
  "memberships": [],
  "publications_preview": [
    {
      "row_order": 0,
      "title": "Modeling Problems in a Regional Labor Market in Poland with MARS and CMARS – supported by Optimization",
      "title_url": "https://ludzie.nauka.gov.pl/ln/profiles/marek.goli%C5%84ski.7SVtrNQCx6J/publications/e32ac741-30ce-426f-ac4f-a7de7fd27fff",
      "authors": "A. Özmen, M. Graczyk-Kucharska [...] M. Goliński , ... (+6)",
      "publication_type": "Artykuł , Engineering Management in Production and Services",
      "year": "2025",
      "doi": "10.2478/emj-2025-0005",
      "doi_url": "https://www.doi.org/10.2478/emj-2025-0005",
      "source": "Źródło danych: Polska Bibliografia Naukowa"
    },
    {
      "row_order": 1,
      "title": "Modelling problems in a regional labour market in Poland with MARS and CMARS — supported by optimisation",
      "title_url": "https://ludzie.nauka.gov.pl/ln/profiles/marek.goli%C5%84ski.7SVtrNQCx6J/publications/13ac73a8-0fee-4a05-b027-7d3d0a4ffa38",
      "authors": "A. Özmen, M. Graczyk-Kucharska [...] M. Goliński , ... (+6)",
      "publication_type": "Artykuł , Engineering Management in Production and Services",
      "year": "2025",
      "doi": "10.2478/emj-2025-0005",
      "doi_url": "https://www.doi.org/10.2478/emj-2025-0005",
      "source": "Źródło danych: OpenAIRE"
    },
    {
      "row_order": 2,
      "title": "Bibliometric Analysis in Family Business Brands",
      "title_url": "https://ludzie.nauka.gov.pl/ln/profiles/marek.goli%C5%84ski.7SVtrNQCx6J/publications/e11d0ecf-ef0e-47ae-be72-3598475219d6",
      "authors": "M. Goliński , K. Hojka",
      "publication_type": "Artykuł , Annales Universitatis Mariae Curie-Skłodowska, sectio H – Oeconomia",
      "year": "2024",
      "doi": "10.17951/h.2024.58.4.25-45",
      "doi_url": "https://www.doi.org/10.17951/h.2024.58.4.25-45",
      "source": "Źródło danych: OpenAIRE"
    }
  ],
  "research_work": {
    "author": [],
    "promoter": [
      {
        "row_order": 0,
        "title": "Metoda zarządzania jakością zintegrowanej komunikacji marketingowej przedsiębiorstwa przemysłowego",
        "title_url": "https://ludzie.nauka.gov.pl/ln/profiles/marek.goli%C5%84ski.7SVtrNQCx6J/research-work/8ccf71b8-8946-435c-a857-0b02e55444ac",
        "description": "Praca doktorska Źródło danych: Nauka Polska",
        "source": "Źródło danych: Nauka Polska"
      }
    ],
    "reviewer": []
  },
  "external_profiles": [
    {
      "label": "Nauka Polska",
      "url": "https://archiwum.nauka-polska.pl/#/profile/scientist?id=229153"
    }
  ],
  "tag_cloud": [
    "тепломассообменные аппараты",
    "war responsibility voluntary trials emperor shōwa higashikuni naruhiko shidehara kijūrō yoshida shigeru",
    "vosviewer",
    "scopus",
    "zarządzanie kompetencjami",
    "metody statystyczne",
    "family business",
    "social competences",
    "художественная литература",
    "human resource management"
  ],
  "coworkers": []
}