{
  "profile_url": "https://ludzie.nauka.gov.pl/ln/profiles/krzysztof.wielgus.ljSBObfTSwS",
  "slug": "krzysztof.wielgus",
  "profile_id": "ljSBObfTSwS",
  "full_name": "dr inż. arch. Krzysztof Jan Wielgus",
  "orcid": "0000-0003-1663-5740",
  "orcid_url": "https://orcid.org/0000-0003-1663-5740",
  "breadcrumb_name": "Krzysztof Wielgus",
  "current_employment_summary": [
    "Politechnika Krakowska im. Tadeusza Kościuszki"
  ],
  "discipline_summary": [
    "dziedzina nauk inżynieryjno-technicznych"
  ],
  "specializations": [
    "architektura krajobrazu",
    "historia",
    "teoria i konserwacja zabytków inżynierii w krajobrazie"
  ],
  "tab_menu": [
    {
      "label": "Profil",
      "href": "https://ludzie.nauka.gov.pl/ln/profiles/krzysztof.wielgus.ljSBObfTSwS",
      "aria_disabled": null
    },
    {
      "label": "Publikacje",
      "href": "https://ludzie.nauka.gov.pl/ln/profiles/krzysztof.wielgus.ljSBObfTSwS/publications",
      "aria_disabled": null
    },
    {
      "label": "Dorobek artystyczny",
      "href": "https://ludzie.nauka.gov.pl/ln/profiles/krzysztof.wielgus.ljSBObfTSwS/achievement",
      "aria_disabled": "true"
    },
    {
      "label": "Patenty i prawa ochronne",
      "href": "https://ludzie.nauka.gov.pl/ln/profiles/krzysztof.wielgus.ljSBObfTSwS/patents",
      "aria_disabled": "true"
    },
    {
      "label": "Projekty",
      "href": "https://ludzie.nauka.gov.pl/ln/profiles/krzysztof.wielgus.ljSBObfTSwS/projects",
      "aria_disabled": null
    },
    {
      "label": "Postępowania awansowe",
      "href": "https://ludzie.nauka.gov.pl/ln/profiles/krzysztof.wielgus.ljSBObfTSwS/research-work",
      "aria_disabled": null
    }
  ],
  "employment_history": [
    {
      "row_order": 0,
      "period": "41 lat 7 miesięcy",
      "duration": null,
      "institution": "Politechnika Krakowska im. Tadeusza Kościuszki",
      "institution_url": "https://radon.nauka.gov.pl/dane/profil/7a7e1b21-0684-43f6-a0d6-5404df34ac74",
      "source_json": [
        "Źródło danych: POL-on"
      ]
    }
  ],
  "degrees_and_titles": [
    {
      "row_order": 0,
      "year": "1997",
      "degree_or_title": "Doktor",
      "details_json": [
        "nauki techniczne / architektura i urbanistyka",
        "Nadanie stopnia"
      ],
      "linked_entities_json": [
        {
          "label": "Politechnika Krakowska im. Tadeusza Kościuszki",
          "href": "https://radon.nauka.gov.pl/dane/profil/7a7e1b21-0684-43f6-a0d6-5404df34ac74"
        }
      ],
      "source_json": [
        "Źródło danych: POL-on"
      ]
    },
    {
      "row_order": 1,
      "year": "1985",
      "degree_or_title": "Magister inżynier architekt",
      "details_json": [
        "architektura",
        "Nadanie tytułu",
        "Politechnika Krakowska",
        "Rejestracja tytułu"
      ],
      "linked_entities_json": [
        {
          "label": "Politechnika Krakowska im. Tadeusza Kościuszki >",
          "href": "https://radon.nauka.gov.pl/dane/profil/7a7e1b21-0684-43f6-a0d6-5404df34ac74"
        }
      ],
      "source_json": [
        "Źródło danych: POL-on"
      ]
    }
  ],
  "memberships": [],
  "publications_preview": [
    {
      "row_order": 0,
      "title": "Współczesna doktryna konserwatorska w świetle Karty Weneckiej. Tom 1",
      "title_url": "https://ludzie.nauka.gov.pl/ln/profiles/krzysztof.wielgus.ljSBObfTSwS/publications/e6a99aba-e16c-4d60-a0ab-50e092f59076",
      "authors": "K. Pałubska, K. Wielgus , K. Zimna-Kawecka",
      "publication_type": "Książka , Uniwersytet Kardynała Stefana Wyszyńskiego w Warszawie",
      "year": "2025",
      "doi": null,
      "doi_url": null,
      "source": "Źródło danych: Polska Bibliografia Naukowa"
    },
    {
      "row_order": 1,
      "title": "Muzeum Lotnictwa Polskiego w Krakowie – 60 lat tradycji",
      "title_url": "https://ludzie.nauka.gov.pl/ln/profiles/krzysztof.wielgus.ljSBObfTSwS/publications/364e5194-95c8-46a7-91d6-5f112ffa2bda",
      "authors": "K. Mroczkowski, P. Wierzbicki, K. Wielgus , ... (+3)",
      "publication_type": "Książka , Muzeum Lotnictwa Polskiego",
      "year": "2023",
      "doi": null,
      "doi_url": null,
      "source": "Źródło danych: Polska Bibliografia Naukowa"
    },
    {
      "row_order": 2,
      "title": "Values as a base for the viable adaptive reuse of fortified heritage in urban contexts",
      "title_url": "https://ludzie.nauka.gov.pl/ln/profiles/krzysztof.wielgus.ljSBObfTSwS/publications/911ca54b-d986-4196-8070-b7f7999720ef",
      "authors": "A. Staniewska, J. Ebejer [...] K. Wielgus , ... (+2)",
      "publication_type": "Artykuł , Muzeologia a Kulturne Dedicstvo",
      "year": "2023",
      "doi": "10.46284/mkd.2023.11.2.3",
      "doi_url": "https://www.doi.org/10.46284/mkd.2023.11.2.3",
      "source": "Źródło danych: Polska Bibliografia Naukowa"
    }
  ],
  "research_work": {
    "author": [
      {
        "row_order": 0,
        "title": "Rola historycznych terenów lotniczych w kształtowaniu krajobrazu",
        "title_url": "https://ludzie.nauka.gov.pl/ln/profiles/krzysztof.wielgus.ljSBObfTSwS/research-work/1d2a7da6-073c-41bd-b3a0-e5f1e67d4c1b",
        "description": "Praca doktorska Źródło danych: Nauka Polska",
        "source": "Źródło danych: Nauka Polska"
      },
      {
        "row_order": 1,
        "title": "Zapis krajobrazu otwartego",
        "title_url": "https://ludzie.nauka.gov.pl/ln/profiles/krzysztof.wielgus.ljSBObfTSwS/research-work/1a009906-a7f2-4a14-a4f5-5c8eea7d703a",
        "description": null,
        "source": "Źródło danych: Nauka Polska"
      }
    ],
    "promoter": [
      {
        "row_order": 0,
        "title": "Bitwa Krakowska 1914 oraz inne ślady działań militarnych na terenach podkrakowskich w świetle badań archeologicznych, historycznych i architektonicznych",
        "title_url": "https://ludzie.nauka.gov.pl/ln/profiles/krzysztof.wielgus.ljSBObfTSwS/research-work/2d8e152b-a03a-4c30-a185-52c2d83da981",
        "description": "Praca doktorska Źródło danych: Nauka Polska",
        "source": "Źródło danych: Nauka Polska"
      }
    ],
    "reviewer": []
  },
  "external_profiles": [
    {
      "label": "Nauka Polska",
      "url": "https://archiwum.nauka-polska.pl/#/profile/scientist?id=85493"
    }
  ],
  "tag_cloud": [
    "zabytkowe tereny zieleni",
    "krajobraz chroniony",
    "historical green areas",
    "dziedzictwo kulturowe",
    "architektura krajobrazu",
    "landscape architecture",
    "fortyfikacja",
    "urban green 690 |a fortification",
    "cultural heritage",
    "zieleń miejska"
  ],
  "coworkers": []
}