{
  "profile_url": "https://ludzie.nauka.gov.pl/ln/profiles/agata.mikrut-kusy.XdI6hPcxb51",
  "slug": "agata.mikrut-kusy",
  "profile_id": "XdI6hPcxb51",
  "full_name": "dr inż. arch. Agata Katarzyna Mikrut-Kusy",
  "orcid": "0000-0002-4703-8167",
  "orcid_url": "https://orcid.org/0000-0002-4703-8167",
  "breadcrumb_name": "Agata Mikrut-Kusy",
  "current_employment_summary": [
    "Politechnika Rzeszowska im. Ignacego Łukasiewicza"
  ],
  "discipline_summary": [
    "dziedzina nauk inżynieryjno-technicznych",
    "dziedzina sztuki"
  ],
  "specializations": [],
  "tab_menu": [
    {
      "label": "Profil",
      "href": "https://ludzie.nauka.gov.pl/ln/profiles/agata.mikrut-kusy.XdI6hPcxb51",
      "aria_disabled": null
    },
    {
      "label": "Publikacje",
      "href": "https://ludzie.nauka.gov.pl/ln/profiles/agata.mikrut-kusy.XdI6hPcxb51/publications",
      "aria_disabled": null
    },
    {
      "label": "Dorobek artystyczny",
      "href": "https://ludzie.nauka.gov.pl/ln/profiles/agata.mikrut-kusy.XdI6hPcxb51/achievement",
      "aria_disabled": "true"
    },
    {
      "label": "Patenty i prawa ochronne",
      "href": "https://ludzie.nauka.gov.pl/ln/profiles/agata.mikrut-kusy.XdI6hPcxb51/patents",
      "aria_disabled": "true"
    },
    {
      "label": "Projekty",
      "href": "https://ludzie.nauka.gov.pl/ln/profiles/agata.mikrut-kusy.XdI6hPcxb51/projects",
      "aria_disabled": "true"
    },
    {
      "label": "Postępowania awansowe",
      "href": "https://ludzie.nauka.gov.pl/ln/profiles/agata.mikrut-kusy.XdI6hPcxb51/research-work",
      "aria_disabled": null
    }
  ],
  "employment_history": [
    {
      "row_order": 0,
      "period": "9 lat 6 miesięcy",
      "duration": null,
      "institution": "Politechnika Rzeszowska im. Ignacego Łukasiewicza",
      "institution_url": "https://radon.nauka.gov.pl/dane/profil/63374761-1ae0-43c0-9fa0-dd7d530ea4ab",
      "source_json": [
        "Źródło danych: POL-on"
      ]
    }
  ],
  "degrees_and_titles": [
    {
      "row_order": 0,
      "year": "2021",
      "degree_or_title": "Doktor",
      "details_json": [
        "dziedzina nauk inżynieryjno-technicznych / architektura i urbanistyka",
        "Nadanie stopnia"
      ],
      "linked_entities_json": [
        {
          "label": "Politechnika Wrocławska",
          "href": "https://radon.nauka.gov.pl/dane/profil/dbdda9a7-f6f7-44e8-af1d-9863e2256ca3"
        }
      ],
      "source_json": [
        "Źródło danych: POL-on"
      ]
    },
    {
      "row_order": 1,
      "year": "2016",
      "degree_or_title": "Magister inżynier architekt",
      "details_json": [
        "architektura",
        "Nadanie tytułu",
        "Politechnika Rzeszowska im. I. Łukasiewicza",
        "Rejestracja tytułu"
      ],
      "linked_entities_json": [
        {
          "label": "Politechnika Rzeszowska im. Ignacego Łukasiewicza >",
          "href": "https://radon.nauka.gov.pl/dane/profil/63374761-1ae0-43c0-9fa0-dd7d530ea4ab"
        }
      ],
      "source_json": [
        "Źródło danych: POL-on"
      ]
    }
  ],
  "memberships": [],
  "publications_preview": [
    {
      "row_order": 0,
      "title": "Facade colors in the historic urban fabric of small former towns in Subcarpathia: the case of market squer in Nowy Żmigród",
      "title_url": "https://ludzie.nauka.gov.pl/ln/profiles/agata.mikrut-kusy.XdI6hPcxb51/publications/12c8585d-ad68-44bc-8b90-801c5901b622",
      "authors": "A. Martyka, A. Mikrut-Kusy",
      "publication_type": "Artykuł , Czasopismo Techniczne/Technical Transactions",
      "year": "2025",
      "doi": null,
      "doi_url": null,
      "source": "Źródło danych: Polska Bibliografia Naukowa"
    },
    {
      "row_order": 1,
      "title": "Rzeszow Castle: History and Contemporaneity - proposal for a new interior adaptation",
      "title_url": "https://ludzie.nauka.gov.pl/ln/profiles/agata.mikrut-kusy.XdI6hPcxb51/publications/a2fc2c2c-9ec4-456a-a999-185cb47b34d7",
      "authors": "M. Gosztyła, A. Mikrut-Kusy , K. Gołąbek",
      "publication_type": "Artykuł , Architektonické listy Fakulty architektúry STU",
      "year": "2023",
      "doi": "10.2478/alfa-2023-0007",
      "doi_url": "https://www.doi.org/10.2478/alfa-2023-0007",
      "source": "Źródło danych: OpenAIRE"
    },
    {
      "row_order": 2,
      "title": "Selected aspects of monuments protection in Poland in the inter war period",
      "title_url": "https://ludzie.nauka.gov.pl/ln/profiles/agata.mikrut-kusy.XdI6hPcxb51/publications/f9e70071-820a-4dc6-a2e5-2a48d8833a5a",
      "authors": null,
      "publication_type": "Artykuł , Journal of Civil Engineering, Environment and Architecture",
      "year": "2023",
      "doi": null,
      "doi_url": null,
      "source": "Źródło danych: Biblioteka Nauki"
    }
  ],
  "research_work": {
    "author": [
      {
        "row_order": 0,
        "title": "Zabudowa przyrynkowa miasta Przeworska",
        "title_url": "https://ludzie.nauka.gov.pl/ln/profiles/agata.mikrut-kusy.XdI6hPcxb51/research-work/85245985-2845-4b5d-801b-f8efceb15c15",
        "description": "Praca doktorska Źródło danych: Nauka Polska",
        "source": "Źródło danych: Nauka Polska"
      }
    ],
    "promoter": [],
    "reviewer": []
  },
  "external_profiles": [
    {
      "label": "Nauka Polska",
      "url": "https://archiwum.nauka-polska.pl/#/profile/scientist?id=308079"
    }
  ],
  "tag_cloud": [],
  "coworkers": []
}