{
  "profile_url": "https://ludzie.nauka.gov.pl/ln/profiles/agata.%C5%82amacz.YtnGSgIeYkK",
  "slug": "agata.łamacz",
  "profile_id": "YtnGSgIeYkK",
  "full_name": "dr hab. inż. Agata Iwona Łamacz",
  "orcid": "0000-0003-1496-6140",
  "orcid_url": "https://orcid.org/0000-0003-1496-6140",
  "breadcrumb_name": "Agata Łamacz",
  "current_employment_summary": [
    "Politechnika Wrocławska"
  ],
  "discipline_summary": [
    "dziedzina nauk inżynieryjno-technicznych"
  ],
  "specializations": [],
  "tab_menu": [
    {
      "label": "Profil",
      "href": "https://ludzie.nauka.gov.pl/ln/profiles/agata.%C5%82amacz.YtnGSgIeYkK",
      "aria_disabled": null
    },
    {
      "label": "Publikacje",
      "href": "https://ludzie.nauka.gov.pl/ln/profiles/agata.%C5%82amacz.YtnGSgIeYkK/publications",
      "aria_disabled": null
    },
    {
      "label": "Dorobek artystyczny",
      "href": "https://ludzie.nauka.gov.pl/ln/profiles/agata.%C5%82amacz.YtnGSgIeYkK/achievement",
      "aria_disabled": "true"
    },
    {
      "label": "Patenty i prawa ochronne",
      "href": "https://ludzie.nauka.gov.pl/ln/profiles/agata.%C5%82amacz.YtnGSgIeYkK/patents",
      "aria_disabled": "true"
    },
    {
      "label": "Projekty",
      "href": "https://ludzie.nauka.gov.pl/ln/profiles/agata.%C5%82amacz.YtnGSgIeYkK/projects",
      "aria_disabled": null
    },
    {
      "label": "Postępowania awansowe",
      "href": "https://ludzie.nauka.gov.pl/ln/profiles/agata.%C5%82amacz.YtnGSgIeYkK/research-work",
      "aria_disabled": null
    }
  ],
  "employment_history": [
    {
      "row_order": 0,
      "period": "10 lat 6 miesięcy",
      "duration": null,
      "institution": "Politechnika Wrocławska",
      "institution_url": "https://radon.nauka.gov.pl/dane/profil/dbdda9a7-f6f7-44e8-af1d-9863e2256ca3",
      "source_json": [
        "Źródło danych: POL-on"
      ]
    },
    {
      "row_order": 1,
      "period": "10 lat 6 miesięcy",
      "duration": null,
      "institution": "Centrum Materiałów Polimerowych i Węglowych Polskiej Akademii Nauk",
      "institution_url": "https://radon.nauka.gov.pl/dane/profil/fee3c56b-eccc-4eb9-bca2-5913db555e88",
      "source_json": [
        "Źródło danych: POL-on"
      ]
    }
  ],
  "degrees_and_titles": [
    {
      "row_order": 0,
      "year": "2024",
      "degree_or_title": "Doktor habilitowany",
      "details_json": [
        "dziedzina nauk inżynieryjno-technicznych / inżynieria chemiczna",
        "Nadanie stopnia"
      ],
      "linked_entities_json": [
        {
          "label": "Politechnika Wrocławska",
          "href": "https://radon.nauka.gov.pl/dane/profil/dbdda9a7-f6f7-44e8-af1d-9863e2256ca3"
        }
      ],
      "source_json": [
        "Źródło danych: POL-on"
      ]
    },
    {
      "row_order": 1,
      "year": "2013",
      "degree_or_title": "Doktor",
      "details_json": [
        "dziedzina nauk technicznych / technologia chemiczna",
        "Nadanie stopnia",
        "Rejestracja stopnia"
      ],
      "linked_entities_json": [
        {
          "label": "Politechnika Śląska; Wydział Chemiczny",
          "href": "https://radon.nauka.gov.pl/dane/profil/ff6c8bd1-4434-47ee-aff6-85683bd6d26d"
        },
        {
          "label": "Politechnika Śląska >",
          "href": "https://radon.nauka.gov.pl/dane/profil/d2b78be5-640c-4efd-870a-a0e84067d609"
        }
      ],
      "source_json": [
        "Źródło danych: POL-on"
      ]
    },
    {
      "row_order": 2,
      "year": "2004",
      "degree_or_title": "Magister inżynier",
      "details_json": [
        "technologia chemiczna",
        "Nadanie tytułu",
        "Rejestracja tytułu"
      ],
      "linked_entities_json": [
        {
          "label": "Politechnika Śląska",
          "href": "https://radon.nauka.gov.pl/dane/profil/d2b78be5-640c-4efd-870a-a0e84067d609"
        },
        {
          "label": "Politechnika Wrocławska >",
          "href": "https://radon.nauka.gov.pl/dane/profil/dbdda9a7-f6f7-44e8-af1d-9863e2256ca3"
        }
      ],
      "source_json": [
        "Źródło danych: POL-on"
      ]
    }
  ],
  "memberships": [],
  "publications_preview": [
    {
      "row_order": 0,
      "title": "Modern catalytic materials for the oxygen evolution reaction",
      "title_url": "https://ludzie.nauka.gov.pl/ln/profiles/agata.%C5%82amacz.YtnGSgIeYkK/publications/d68d57db-d1d5-4d6b-afec-a90e88d042e1",
      "authors": "M. Trębala, A. Łamacz",
      "publication_type": "Artykuł , Molecules",
      "year": "2025",
      "doi": "10.3390/molecules30081656",
      "doi_url": "https://www.doi.org/10.3390/molecules30081656",
      "source": "Źródło danych: Polska Bibliografia Naukowa"
    },
    {
      "row_order": 1,
      "title": "Nickel mobilization during single-stage aqueous mineral carbonation of serpentinized peridotite at 185 °C and PCO₂ of 100 bar",
      "title_url": "https://ludzie.nauka.gov.pl/ln/profiles/agata.%C5%82amacz.YtnGSgIeYkK/publications/015501c4-5c48-4b28-ad3d-9b75232c268a",
      "authors": "B. Cieślik, M. Róziewicz [...] A. Łamacz , ... (+7)",
      "publication_type": "Artykuł , Journal of CO2 Utilization",
      "year": "2025",
      "doi": "10.1016/j.jcou.2025.103119",
      "doi_url": "https://www.doi.org/10.1016/j.jcou.2025.103119",
      "source": "Źródło danych: Polska Bibliografia Naukowa"
    },
    {
      "row_order": 2,
      "title": "On the HKUST-1/GO and HKUST-1/rGO composites: the impact of synthesis method on physicochemical properties",
      "title_url": "https://ludzie.nauka.gov.pl/ln/profiles/agata.%C5%82amacz.YtnGSgIeYkK/publications/dc70ef4a-fa01-4894-a3ef-d38302966513",
      "authors": "P. Jagódka, K. Matus, A. Łamacz",
      "publication_type": "Artykuł , Molecules",
      "year": "2022",
      "doi": "10.3390/molecules27207082",
      "doi_url": "https://www.doi.org/10.3390/molecules27207082",
      "source": "Źródło danych: OpenAIRE"
    }
  ],
  "research_work": {
    "author": [
      {
        "row_order": 0,
        "title": "Zastosowanie katalizatorów dwufunkcyjnych w procesach konwersji węglowodorów do gazu syntezowego",
        "title_url": "https://ludzie.nauka.gov.pl/ln/profiles/agata.%C5%82amacz.YtnGSgIeYkK/research-work/f03bed98-8e13-480e-b0d5-9c628cddca26",
        "description": "Praca habilitacyjna Źródło danych: POL-on , Nauka Polska",
        "source": "Źródło danych: POL-on , Nauka Polska"
      },
      {
        "row_order": 1,
        "title": "Study of Catalytic Removal of NOx from Coal Combustion Flue Gases and Tar from Coal Gasification on CeZrO2 Supported Metal Catalysts",
        "title_url": "https://ludzie.nauka.gov.pl/ln/profiles/agata.%C5%82amacz.YtnGSgIeYkK/research-work/b281d142-1438-47c1-90b9-a7c7a022459b",
        "description": "Praca doktorska Źródło danych: Nauka Polska",
        "source": "Źródło danych: Nauka Polska"
      }
    ],
    "promoter": [
      {
        "row_order": 0,
        "title": "Synteza, charakterystyka oraz właściwości katalityczne szkieletów metaloorganicznych zawierających kationy ceru",
        "title_url": "https://ludzie.nauka.gov.pl/ln/profiles/agata.%C5%82amacz.YtnGSgIeYkK/research-work/e07fd051-469a-40bf-9cd2-b04483d446e7",
        "description": "Praca doktorska Źródło danych: Nauka Polska",
        "source": "Źródło danych: Nauka Polska"
      }
    ],
    "reviewer": [
      {
        "row_order": 0,
        "title": "Nowe układy katalityczne dla reakcji epoksydów z bezwodnikami kwasowymi",
        "title_url": "https://ludzie.nauka.gov.pl/ln/profiles/agata.%C5%82amacz.YtnGSgIeYkK/research-work/8cbabcce-ac00-4455-bf89-5dbf3a504346",
        "description": "Praca doktorska Źródło danych: POL-on",
        "source": "Źródło danych: POL-on"
      }
    ]
  },
  "external_profiles": [
    {
      "label": "Nauka Polska",
      "url": "https://archiwum.nauka-polska.pl/#/profile/scientist?id=251197"
    }
  ],
  "tag_cloud": [
    "sorpcja co2",
    "wgs",
    "uwodornienie co2",
    "mof",
    "uio-66",
    "cnts",
    "cerium",
    "cer",
    "nikiel",
    "usuwanie smół"
  ],
  "coworkers": []
}